typeid/__init__.py
typeid/base32.py
typeid/cli.py
typeid/constants.py
typeid/errors.py
typeid/factory.py
typeid/py.typed
typeid/typeid.py
typeid/validation.py
typeid/explain/__init__.py
typeid/explain/discovery.py
typeid/explain/engine.py
typeid/explain/formatters.py
typeid/explain/model.py
typeid/explain/registry.py
typeid_python-0.3.4.dist-info/METADATA
typeid_python-0.3.4.dist-info/WHEEL
typeid_python-0.3.4.dist-info/entry_points.txt
typeid_python-0.3.4.dist-info/licenses/LICENSE
typeid_python-0.3.4.dist-info/RECORD
