Metadata-Version: 2.4
Name: typeid-python
Version: 0.3.4
Summary: Python implementation of TypeIDs: type-safe, K-sortable, and globally unique identifiers inspired by Stripe IDs
Project-URL: Homepage, https://github.com/akhundMurad/typeid-python
Project-URL: Repository, https://github.com/akhundMurad/typeid-python
Project-URL: Bug Tracker, https://github.com/akhundMurad/typeid-python/issues
Author-email: Murad Akhundov <akhundov1murad@gmail.com>
License-Expression: MIT
License-File: LICENSE
Keywords: guid,typeid,uuid,uuid6
Classifier: Development Status :: 3 - Alpha
Classifier: License :: OSI Approved :: MIT License
Classifier: Operating System :: OS Independent
Classifier: Programming Language :: Python :: 3.10
Classifier: Programming Language :: Python :: 3.11
Classifier: Programming Language :: Python :: 3.12
Classifier: Programming Language :: Python :: 3.13
Classifier: Programming Language :: Python :: 3.14
Requires-Python: <4,>=3.10
Requires-Dist: uuid6<2026.0.0,>=2024.7.10
Provides-Extra: cli
Requires-Dist: click; extra == 'cli'
Provides-Extra: yaml
Requires-Dist: pyyaml; extra == 'yaml'
